gtfsdb/__init__.py
gtfsdb/api.py
gtfsdb/config.py
gtfsdb/scripts.py
gtfsdb/util.py
gtfsdb/configs/app.ini
gtfsdb/data/route_filter.txt
gtfsdb/data/route_type.txt
gtfsdb/model/__init__.py
gtfsdb/model/agency.py
gtfsdb/model/base.py
gtfsdb/model/block.py
gtfsdb/model/calendar.py
gtfsdb/model/db.py
gtfsdb/model/fare.py
gtfsdb/model/feed_info.py
gtfsdb/model/frequency.py
gtfsdb/model/gtfs.py
gtfsdb/model/pattern.py
gtfsdb/model/pattern_base.py
gtfsdb/model/route.py
gtfsdb/model/route_base.py
gtfsdb/model/route_stop.py
gtfsdb/model/route_stop_base.py
gtfsdb/model/shape.py
gtfsdb/model/stop.py
gtfsdb/model/stop_base.py
gtfsdb/model/stop_feature.py
gtfsdb/model/stop_time.py
gtfsdb/model/transfer.py
gtfsdb/model/trip.py
gtfsdb/tests/__init__.py
gtfsdb/tests/base.py
gtfsdb/tests/test_current.py
gtfsdb/tests/test_dates.py
gtfsdb/tests/test_geom_queries.py
gtfsdb/tests/test_load.py
gtfsdb/tests/test_model.py
gtfsdb-0.6.0.dist-info/LICENSE.txt
gtfsdb-0.6.0.dist-info/METADATA
gtfsdb-0.6.0.dist-info/WHEEL
gtfsdb-0.6.0.dist-info/entry_points.txt
gtfsdb-0.6.0.dist-info/top_level.txt
gtfsdb-0.6.0.dist-info/RECORD
