Metadata-Version: 2.1
Name: gtfsdb
Version: 0.6.0
Summary: GTFS Database
Author: Open Transit Tools
Author-email: info@opentransittools.org
Keywords: GTFS
Classifier: Development Status :: 5 - Production/Stable
Classifier: Environment :: Console
Classifier: Intended Audience :: Developers
Classifier: License :: OSI Approved :: Mozilla Public License 2.0 (MPL 2.0)
Classifier: Natural Language :: English
Classifier: Programming Language :: Python :: 2.7
Classifier: Programming Language :: Python :: 3.7
License-File: LICENSE.txt
Requires-Dist: geoalchemy2
Requires-Dist: sqlalchemy
Provides-Extra: dev
Provides-Extra: oracle
Requires-Dist: cx-oracle (>=5.1) ; extra == 'oracle'
Provides-Extra: postgresql
Requires-Dist: psycopg2-binary ; extra == 'postgresql'
